{
  "manifestVersion": "3.2",
  "proxies": [
    {
      "address": "0xf4B146FbA71F41E0592668ffbF264F1D186b2Ca8",
      "txHash": "0xbc1885402648e0bf3036c76b41c429a3f1f4f3c96c728845b68bff413509b4dd",
      "kind": "uups"
    },
    {
      "address": "0x8198f5d8F8CfFE8f9C413d98a0A55aEB8ab9FbB7",
      "txHash": "0x3ebdab401b6c1802f0f89482696a417fefde9891e8b41f7105104b954c7d93b5",
      "kind": "uups"
    },
    {
      "address": "0x172076E0166D1F9Cc711C77Adf8488051744980C",
      "txHash": "0x9be260965b56e504f40eb10396d5a3f0c209aced7532c2499af01cea949d5c3f",
      "kind": "uups"
    },
    {
      "address": "0x7a2088a1bFc9d81c55368AE168C2C02570cB814F",
      "txHash": "0x468afedfcc702ce12ef91da3d494e288f1a9d083ad1bd4f715af942a9b1da1a8",
      "kind": "uups"
    },
    {
      "address": "0xE6E340D132b5f46d1e472DebcD681B2aBc16e57E",
      "txHash": "0xb4374b44ab83609d973739da5554af7056ab0feb9adbd796e361c6f84177a0fc",
      "kind": "uups"
    }
  ],
  "impls": {
    "0047d1a8052f1671f437451908f1fd33089a7e51411ee3254ff844b83c0778e8": {
      "address": "0x36b58F5C1969B7b6591D752ea6F5486D069010AB",
      "txHash": "0xa0aee012994232c1ca17533469737f40a2c5be6554f61cdf3a85630693360447",
      "layout": {
        "storage": [
          {
            "label": "_initialized",
            "offset": 0,
            "slot": "0",
            "type": "t_uint8",
            "contract": "Initializable",
            "src": "@openzeppelin/contracts-upgradeable/proxy/utils/Initializable.sol:62",
            "retypedFrom": "bool"
          },
          {
            "label": "_initializing",
            "offset": 1,
            "slot": "0",
            "type": "t_bool",
            "contract": "Initializable",
            "src": "@openzeppelin/contracts-upgradeable/proxy/utils/Initializable.sol:67"
          },
          {
            "label": "__gap",
            "offset": 0,
            "slot": "1",
            "type": "t_array(t_uint256)50_storage",
            "contract": "ERC1967UpgradeUpgradeable",
            "src": "@openzeppelin/contracts-upgradeable/proxy/ERC1967/ERC1967UpgradeUpgradeable.sol:211"
          },
          {
            "label": "__gap",
            "offset": 0,
            "slot": "51",
            "type": "t_array(t_uint256)50_storage",
            "contract": "UUPSUpgradeable",
            "src": "@openzeppelin/contracts-upgradeable/proxy/utils/UUPSUpgradeable.sol:107"
          },
          {
            "label": "__gap",
            "offset": 0,
            "slot": "101",
            "type": "t_array(t_uint256)50_storage",
            "contract": "ContextUpgradeable",
            "src": "@openzeppelin/contracts-upgradeable/utils/ContextUpgradeable.sol:36"
          },
          {
            "label": "__gap",
            "offset": 0,
            "slot": "151",
            "type": "t_array(t_uint256)50_storage",
            "contract": "ERC165Upgradeable",
            "src": "@openzeppelin/contracts-upgradeable/utils/introspection/ERC165Upgradeable.sol:41"
          },
          {
            "label": "_roles",
            "offset": 0,
            "slot": "201",
            "type": "t_mapping(t_bytes32,t_struct(RoleData)179_storage)",
            "contract": "AccessControlUpgradeable",
            "src": "@openzeppelin/contracts-upgradeable/access/AccessControlUpgradeable.sol:61"
          },
          {
            "label": "__gap",
            "offset": 0,
            "slot": "202",
            "type": "t_array(t_uint256)49_storage",
            "contract": "AccessControlUpgradeable",
            "src": "@openzeppelin/contracts-upgradeable/access/AccessControlUpgradeable.sol:259"
          },
          {
            "label": "_roleMembers",
            "offset": 0,
            "slot": "251",
            "type": "t_mapping(t_bytes32,t_struct(AddressSet)3096_storage)",
            "contract": "AccessControlEnumerableUpgradeable",
            "src": "@openzeppelin/contracts-upgradeable/access/AccessControlEnumerableUpgradeable.sol:22"
          },
          {
            "label": "__gap",
            "offset": 0,
            "slot": "252",
            "type": "t_array(t_uint256)49_storage",
            "contract": "AccessControlEnumerableUpgradeable",
            "src": "@openzeppelin/contracts-upgradeable/access/AccessControlEnumerableUpgradeable.sol:76"
          },
          {
            "label": "want",
            "offset": 0,
            "slot": "301",
            "type": "t_address",
            "contract": "ReaperBaseStrategyv4",
            "src": "contracts/abstract/ReaperBaseStrategyv4.sol:28"
          },
          {
            "label": "emergencyExit",
            "offset": 20,
            "slot": "301",
            "type": "t_bool",
            "contract": "ReaperBaseStrategyv4",
            "src": "contracts/abstract/ReaperBaseStrategyv4.sol:30"
          },
          {
            "label": "lastHarvestTimestamp",
            "offset": 0,
            "slot": "302",
            "type": "t_uint256",
            "contract": "ReaperBaseStrategyv4",
            "src": "contracts/abstract/ReaperBaseStrategyv4.sol:31"
          },
          {
            "label": "upgradeProposalTime",
            "offset": 0,
            "slot": "303",
            "type": "t_uint256",
            "contract": "ReaperBaseStrategyv4",
            "src": "contracts/abstract/ReaperBaseStrategyv4.sol:33"
          },
          {
            "label": "vault",
            "offset": 0,
            "slot": "304",
            "type": "t_address",
            "contract": "ReaperBaseStrategyv4",
            "src": "contracts/abstract/ReaperBaseStrategyv4.sol:58"
          },
          {
            "label": "tshareToWftmPath",
            "offset": 0,
            "slot": "305",
            "type": "t_array(t_address)dyn_storage",
            "contract": "ReaperStrategyTombMai",
            "src": "contracts/ReaperStrategyTombMai.sol:41"
          },
          {
            "label": "wftmToTombPath",
            "offset": 0,
            "slot": "306",
            "type": "t_array(t_address)dyn_storage",
            "contract": "ReaperStrategyTombMai",
            "src": "contracts/ReaperStrategyTombMai.sol:42"
          },
          {
            "label": "tombToMaiPath",
            "offset": 0,
            "slot": "307",
            "type": "t_array(t_address)dyn_storage",
            "contract": "ReaperStrategyTombMai",
            "src": "contracts/ReaperStrategyTombMai.sol:43"
          },
          {
            "label": "poolId",
            "offset": 0,
            "slot": "308",
            "type": "t_uint256",
            "contract": "ReaperStrategyTombMai",
            "src": "contracts/ReaperStrategyTombMai.sol:49"
          }
        ],
        "types": {
          "t_address": {
            "label": "address",
            "numberOfBytes": "20"
          },
          "t_array(t_address)dyn_storage": {
            "label": "address[]",
            "numberOfBytes": "32"
          },
          "t_array(t_bytes32)dyn_storage": {
            "label": "bytes32[]",
            "numberOfBytes": "32"
          },
          "t_array(t_uint256)49_storage": {
            "label": "uint256[49]",
            "numberOfBytes": "1568"
          },
          "t_array(t_uint256)50_storage": {
            "label": "uint256[50]",
            "numberOfBytes": "1600"
          },
          "t_bool": {
            "label": "bool",
            "numberOfBytes": "1"
          },
          "t_bytes32": {
            "label": "bytes32",
            "numberOfBytes": "32"
          },
          "t_mapping(t_address,t_bool)": {
            "label": "mapping(address => bool)",
            "numberOfBytes": "32"
          },
          "t_mapping(t_bytes32,t_struct(AddressSet)3096_storage)": {
            "label": "mapping(bytes32 => struct EnumerableSetUpgradeable.AddressSet)",
            "numberOfBytes": "32"
          },
          "t_mapping(t_bytes32,t_struct(RoleData)179_storage)": {
            "label": "mapping(bytes32 => struct AccessControlUpgradeable.RoleData)",
            "numberOfBytes": "32"
          },
          "t_mapping(t_bytes32,t_uint256)": {
            "label": "mapping(bytes32 => uint256)",
            "numberOfBytes": "32"
          },
          "t_struct(AddressSet)3096_storage": {
            "label": "struct EnumerableSetUpgradeable.AddressSet",
            "members": [
              {
                "label": "_inner",
                "type": "t_struct(Set)2795_storage",
                "offset": 0,
                "slot": "0"
              }
            ],
            "numberOfBytes": "64"
          },
          "t_struct(RoleData)179_storage": {
            "label": "struct AccessControlUpgradeable.RoleData",
            "members": [
              {
                "label": "members",
                "type": "t_mapping(t_address,t_bool)",
                "offset": 0,
                "slot": "0"
              },
              {
                "label": "adminRole",
                "type": "t_bytes32",
                "offset": 0,
                "slot": "1"
              }
            ],
            "numberOfBytes": "64"
          },
          "t_struct(Set)2795_storage": {
            "label": "struct EnumerableSetUpgradeable.Set",
            "members": [
              {
                "label": "_values",
                "type": "t_array(t_bytes32)dyn_storage",
                "offset": 0,
                "slot": "0"
              },
              {
                "label": "_indexes",
                "type": "t_mapping(t_bytes32,t_uint256)",
                "offset": 0,
                "slot": "1"
              }
            ],
            "numberOfBytes": "64"
          },
          "t_uint256": {
            "label": "uint256",
            "numberOfBytes": "32"
          },
          "t_uint8": {
            "label": "uint8",
            "numberOfBytes": "1"
          }
        }
      }
    },
    "7e3a17ee8158e075c2f4e1b1afeb3ae90647632104ef6600a22bd5ba37aefd78": {
      "address": "0x4A679253410272dd5232B3Ff7cF5dbB88f295319",
      "txHash": "0x528d42a5a0c5e172a1864d37e02ed25e5bbb0731521d0ffce7a3756d2dcb6429",
      "layout": {
        "storage": [
          {
            "label": "_initialized",
            "offset": 0,
            "slot": "0",
            "type": "t_uint8",
            "contract": "Initializable",
            "src": "@openzeppelin\\contracts-upgradeable\\proxy\\utils\\Initializable.sol:62",
            "retypedFrom": "bool"
          },
          {
            "label": "_initializing",
            "offset": 1,
            "slot": "0",
            "type": "t_bool",
            "contract": "Initializable",
            "src": "@openzeppelin\\contracts-upgradeable\\proxy\\utils\\Initializable.sol:67"
          },
          {
            "label": "__gap",
            "offset": 0,
            "slot": "1",
            "type": "t_array(t_uint256)50_storage",
            "contract": "ERC1967UpgradeUpgradeable",
            "src": "@openzeppelin\\contracts-upgradeable\\proxy\\ERC1967\\ERC1967UpgradeUpgradeable.sol:211"
          },
          {
            "label": "__gap",
            "offset": 0,
            "slot": "51",
            "type": "t_array(t_uint256)50_storage",
            "contract": "UUPSUpgradeable",
            "src": "@openzeppelin\\contracts-upgradeable\\proxy\\utils\\UUPSUpgradeable.sol:107"
          },
          {
            "label": "__gap",
            "offset": 0,
            "slot": "101",
            "type": "t_array(t_uint256)50_storage",
            "contract": "ContextUpgradeable",
            "src": "@openzeppelin\\contracts-upgradeable\\utils\\ContextUpgradeable.sol:36"
          },
          {
            "label": "__gap",
            "offset": 0,
            "slot": "151",
            "type": "t_array(t_uint256)50_storage",
            "contract": "ERC165Upgradeable",
            "src": "@openzeppelin\\contracts-upgradeable\\utils\\introspection\\ERC165Upgradeable.sol:41"
          },
          {
            "label": "_roles",
            "offset": 0,
            "slot": "201",
            "type": "t_mapping(t_bytes32,t_struct(RoleData)179_storage)",
            "contract": "AccessControlUpgradeable",
            "src": "@openzeppelin\\contracts-upgradeable\\access\\AccessControlUpgradeable.sol:61"
          },
          {
            "label": "__gap",
            "offset": 0,
            "slot": "202",
            "type": "t_array(t_uint256)49_storage",
            "contract": "AccessControlUpgradeable",
            "src": "@openzeppelin\\contracts-upgradeable\\access\\AccessControlUpgradeable.sol:259"
          },
          {
            "label": "_roleMembers",
            "offset": 0,
            "slot": "251",
            "type": "t_mapping(t_bytes32,t_struct(AddressSet)3096_storage)",
            "contract": "AccessControlEnumerableUpgradeable",
            "src": "@openzeppelin\\contracts-upgradeable\\access\\AccessControlEnumerableUpgradeable.sol:22"
          },
          {
            "label": "__gap",
            "offset": 0,
            "slot": "252",
            "type": "t_array(t_uint256)49_storage",
            "contract": "AccessControlEnumerableUpgradeable",
            "src": "@openzeppelin\\contracts-upgradeable\\access\\AccessControlEnumerableUpgradeable.sol:76"
          },
          {
            "label": "want",
            "offset": 0,
            "slot": "301",
            "type": "t_address",
            "contract": "ReaperBaseStrategyv4",
            "src": "contracts\\abstract\\ReaperBaseStrategyv4.sol:28"
          },
          {
            "label": "emergencyExit",
            "offset": 20,
            "slot": "301",
            "type": "t_bool",
            "contract": "ReaperBaseStrategyv4",
            "src": "contracts\\abstract\\ReaperBaseStrategyv4.sol:30"
          },
          {
            "label": "lastHarvestTimestamp",
            "offset": 0,
            "slot": "302",
            "type": "t_uint256",
            "contract": "ReaperBaseStrategyv4",
            "src": "contracts\\abstract\\ReaperBaseStrategyv4.sol:31"
          },
          {
            "label": "upgradeProposalTime",
            "offset": 0,
            "slot": "303",
            "type": "t_uint256",
            "contract": "ReaperBaseStrategyv4",
            "src": "contracts\\abstract\\ReaperBaseStrategyv4.sol:33"
          },
          {
            "label": "vault",
            "offset": 0,
            "slot": "304",
            "type": "t_address",
            "contract": "ReaperBaseStrategyv4",
            "src": "contracts\\abstract\\ReaperBaseStrategyv4.sol:58"
          },
          {
            "label": "veloSwapPath",
            "offset": 0,
            "slot": "305",
            "type": "t_mapping(t_address,t_mapping(t_address,t_array(t_address)dyn_storage))",
            "contract": "VeloSolidMixin",
            "src": "contracts\\mixins\\VeloSolidMixin.sol:15"
          },
          {
            "label": "gWant",
            "offset": 0,
            "slot": "306",
            "type": "t_contract(IAToken)10381",
            "contract": "ReaperStrategyGranarySupplyOnly",
            "src": "contracts\\ReaperStrategyGranarySupplyOnly.sol:32"
          },
          {
            "label": "rewardClaimingTokens",
            "offset": 0,
            "slot": "307",
            "type": "t_array(t_address)dyn_storage",
            "contract": "ReaperStrategyGranarySupplyOnly",
            "src": "contracts\\ReaperStrategyGranarySupplyOnly.sol:41"
          },
          {
            "label": "steps",
            "offset": 0,
            "slot": "308",
            "type": "t_array(t_array(t_address)2_storage)dyn_storage",
            "contract": "ReaperStrategyGranarySupplyOnly",
            "src": "contracts\\ReaperStrategyGranarySupplyOnly.sol:56"
          }
        ],
        "types": {
          "t_address": {
            "label": "address",
            "numberOfBytes": "20"
          },
          "t_array(t_address)2_storage": {
            "label": "address[2]",
            "numberOfBytes": "64"
          },
          "t_array(t_address)dyn_storage": {
            "label": "address[]",
            "numberOfBytes": "32"
          },
          "t_array(t_array(t_address)2_storage)dyn_storage": {
            "label": "address[2][]",
            "numberOfBytes": "32"
          },
          "t_array(t_bytes32)dyn_storage": {
            "label": "bytes32[]",
            "numberOfBytes": "32"
          },
          "t_array(t_uint256)49_storage": {
            "label": "uint256[49]",
            "numberOfBytes": "1568"
          },
          "t_array(t_uint256)50_storage": {
            "label": "uint256[50]",
            "numberOfBytes": "1600"
          },
          "t_bool": {
            "label": "bool",
            "numberOfBytes": "1"
          },
          "t_bytes32": {
            "label": "bytes32",
            "numberOfBytes": "32"
          },
          "t_contract(IAToken)10381": {
            "label": "contract IAToken",
            "numberOfBytes": "20"
          },
          "t_mapping(t_address,t_array(t_address)dyn_storage)": {
            "label": "mapping(address => address[])",
            "numberOfBytes": "32"
          },
          "t_mapping(t_address,t_bool)": {
            "label": "mapping(address => bool)",
            "numberOfBytes": "32"
          },
          "t_mapping(t_address,t_mapping(t_address,t_array(t_address)dyn_storage))": {
            "label": "mapping(address => mapping(address => address[]))",
            "numberOfBytes": "32"
          },
          "t_mapping(t_bytes32,t_struct(AddressSet)3096_storage)": {
            "label": "mapping(bytes32 => struct EnumerableSetUpgradeable.AddressSet)",
            "numberOfBytes": "32"
          },
          "t_mapping(t_bytes32,t_struct(RoleData)179_storage)": {
            "label": "mapping(bytes32 => struct AccessControlUpgradeable.RoleData)",
            "numberOfBytes": "32"
          },
          "t_mapping(t_bytes32,t_uint256)": {
            "label": "mapping(bytes32 => uint256)",
            "numberOfBytes": "32"
          },
          "t_struct(AddressSet)3096_storage": {
            "label": "struct EnumerableSetUpgradeable.AddressSet",
            "members": [
              {
                "label": "_inner",
                "type": "t_struct(Set)2795_storage",
                "offset": 0,
                "slot": "0"
              }
            ],
            "numberOfBytes": "64"
          },
          "t_struct(RoleData)179_storage": {
            "label": "struct AccessControlUpgradeable.RoleData",
            "members": [
              {
                "label": "members",
                "type": "t_mapping(t_address,t_bool)",
                "offset": 0,
                "slot": "0"
              },
              {
                "label": "adminRole",
                "type": "t_bytes32",
                "offset": 0,
                "slot": "1"
              }
            ],
            "numberOfBytes": "64"
          },
          "t_struct(Set)2795_storage": {
            "label": "struct EnumerableSetUpgradeable.Set",
            "members": [
              {
                "label": "_values",
                "type": "t_array(t_bytes32)dyn_storage",
                "offset": 0,
                "slot": "0"
              },
              {
                "label": "_indexes",
                "type": "t_mapping(t_bytes32,t_uint256)",
                "offset": 0,
                "slot": "1"
              }
            ],
            "numberOfBytes": "64"
          },
          "t_uint256": {
            "label": "uint256",
            "numberOfBytes": "32"
          },
          "t_uint8": {
            "label": "uint8",
            "numberOfBytes": "1"
          }
        }
      }
    }
  }
}
